{
  "schema_version": "company_package.v1",
  "timezone": "UTC+8",
  "exported_at": "2025-12-26 10:54:44",
  "match": {
    "match_id": "2788680",
    "match_time": "2025-12-26 23:00",
    "league": {
      "league_id": 93,
      "league_name": "unknown"
    },
    "home_team": "埃及",
    "away_team": "南非"
  },
  "company": {
    "company_id": "3",
    "company_name": "Crown"
  },
  "markets": {
    "handicap": {
      "events": [
        {
          "event_time": "2025-12-22 20:21",
          "state": "早",
          "is_opening": 0,
          "line": "半球",
          "home_odds": 0.92,
          "away_odds": 0.9,
          "raw_cols": "||0.92|半球|0.90|12-22 20:21|早"
        },
        {
          "event_time": "2025-12-23 00:09",
          "state": "早",
          "is_opening": 0,
          "line": "半球",
          "home_odds": 0.97,
          "away_odds": 0.85,
          "raw_cols": "||0.97|半球|0.85|12-23 00:09|早"
        },
        {
          "event_time": "2025-12-23 00:11",
          "state": "早",
          "is_opening": 0,
          "line": "半球",
          "home_odds": 1.02,
          "away_odds": 0.8,
          "raw_cols": "||1.02|半球|0.80|12-23 00:11|早"
        },
        {
          "event_time": "2025-12-23 06:23",
          "state": "早",
          "is_opening": 0,
          "line": "半球",
          "home_odds": 0.97,
          "away_odds": 0.85,
          "raw_cols": "||0.97|半球|0.85|12-23 06:23|早"
        },
        {
          "event_time": "2025-12-24 04:55",
          "state": "早",
          "is_opening": 0,
          "line": "半球",
          "home_odds": 0.98,
          "away_odds": 0.84,
          "raw_cols": "||0.98|半球|0.84|12-24 04:55|早"
        },
        {
          "event_time": "2025-12-25 06:07",
          "state": "早",
          "is_opening": 0,
          "line": "半球",
          "home_odds": 0.93,
          "away_odds": 0.89,
          "raw_cols": "||0.93|半球|0.89|12-25 06:07|早"
        },
        {
          "event_time": "2025-12-25 12:03",
          "state": "早",
          "is_opening": 0,
          "line": "半球",
          "home_odds": 0.96,
          "away_odds": 0.92,
          "raw_cols": "||0.96|半球|0.92|12-25 12:03|早"
        },
        {
          "event_time": "2025-12-25 12:05",
          "state": "早",
          "is_opening": 0,
          "line": "半球",
          "home_odds": 0.88,
          "away_odds": 0.94,
          "raw_cols": "||0.88|半球|0.94|12-25 12:05|早"
        },
        {
          "event_time": "2025-12-25 21:21",
          "state": "早",
          "is_opening": 0,
          "line": "半球",
          "home_odds": 0.83,
          "away_odds": 0.99,
          "raw_cols": "||0.83|半球|0.99|12-25 21:21|早"
        },
        {
          "event_time": "2025-12-25 23:54",
          "state": "早",
          "is_opening": 0,
          "line": "半球",
          "home_odds": 0.85,
          "away_odds": 0.97,
          "raw_cols": "||0.85|半球|0.97|12-25 23:54|早"
        }
      ],
      "latest": {
        "event_time": "2025-12-25 23:54",
        "state": "早",
        "is_opening": 0,
        "line": "半球",
        "home_odds": 0.85,
        "away_odds": 0.97,
        "raw_cols": "||0.85|半球|0.97|12-25 23:54|早"
      }
    },
    "overunder": {
      "events": [
        {
          "event_time": "2025-12-22 20:21",
          "state": "早",
          "is_opening": 0,
          "line": "2",
          "over_odds": 0.88,
          "under_odds": 0.92,
          "raw_cols": "||0.88|2|0.92|12-22 20:21|早"
        },
        {
          "event_time": "2025-12-22 22:44",
          "state": "早",
          "is_opening": 0,
          "line": "2",
          "over_odds": 0.95,
          "under_odds": 0.85,
          "raw_cols": "||0.95|2|0.85|12-22 22:44|早"
        },
        {
          "event_time": "2025-12-25 12:03",
          "state": "早",
          "is_opening": 0,
          "line": "2",
          "over_odds": 0.99,
          "under_odds": 0.88,
          "raw_cols": "||0.99|2|0.88|12-25 12:03|早"
        },
        {
          "event_time": "2025-12-25 12:05",
          "state": "早",
          "is_opening": 0,
          "line": "2",
          "over_odds": 0.94,
          "under_odds": 0.86,
          "raw_cols": "||0.94|2|0.86|12-25 12:05|早"
        }
      ],
      "latest": {
        "event_time": "2025-12-25 12:05",
        "state": "早",
        "is_opening": 0,
        "line": "2",
        "over_odds": 0.94,
        "under_odds": 0.86,
        "raw_cols": "||0.94|2|0.86|12-25 12:05|早"
      }
    },
    "1x2": {
      "events": [
        {
          "event_time": "2025-12-22 20:21",
          "state": "早",
          "is_opening": 1,
          "home": 1.92,
          "draw": 3.25,
          "away": 4.0,
          "raw_cols": "||1.92|3.25|4.00|12-22 20:21|(初盘)"
        },
        {
          "event_time": "2025-12-22 22:44",
          "state": "早",
          "is_opening": 0,
          "home": 1.92,
          "draw": 3.2,
          "away": 4.05,
          "raw_cols": "||1.92|3.20|4.05|12-22 22:44|早"
        },
        {
          "event_time": "2025-12-23 00:11",
          "state": "早",
          "is_opening": 0,
          "home": 2.02,
          "draw": 3.15,
          "away": 3.7,
          "raw_cols": "||2.02|3.15|3.70|12-23 00:11|早"
        },
        {
          "event_time": "2025-12-23 06:23",
          "state": "早",
          "is_opening": 0,
          "home": 1.97,
          "draw": 3.2,
          "away": 3.85,
          "raw_cols": "||1.97|3.20|3.85|12-23 06:23|早"
        },
        {
          "event_time": "2025-12-24 04:55",
          "state": "早",
          "is_opening": 0,
          "home": 1.98,
          "draw": 3.05,
          "away": 4.1,
          "raw_cols": "||1.98|3.05|4.10|12-24 04:55|早"
        },
        {
          "event_time": "2025-12-25 06:08",
          "state": "早",
          "is_opening": 0,
          "home": 1.94,
          "draw": 3.05,
          "away": 4.1,
          "raw_cols": "||1.94|3.05|4.10|12-25 06:08|早"
        },
        {
          "event_time": "2025-12-25 06:09",
          "state": "早",
          "is_opening": 0,
          "home": 1.93,
          "draw": 3.1,
          "away": 4.2,
          "raw_cols": "||1.93|3.10|4.20|12-25 06:09|早"
        },
        {
          "event_time": "2025-12-25 12:05",
          "state": "早",
          "is_opening": 0,
          "home": 1.88,
          "draw": 3.1,
          "away": 4.45,
          "raw_cols": "||1.88|3.10|4.45|12-25 12:05|早"
        },
        {
          "event_time": "2025-12-25 21:22",
          "state": "早",
          "is_opening": 0,
          "home": 1.83,
          "draw": 3.15,
          "away": 4.65,
          "raw_cols": "||1.83|3.15|4.65|12-25 21:22|早"
        },
        {
          "event_time": "2025-12-25 23:54",
          "state": "早",
          "is_opening": 0,
          "home": 1.85,
          "draw": 3.15,
          "away": 4.55,
          "raw_cols": "||1.85|3.15|4.55|12-25 23:54|早"
        }
      ],
      "latest": {
        "event_time": "2025-12-25 23:54",
        "state": "早",
        "is_opening": 0,
        "home": 1.85,
        "draw": 3.15,
        "away": 4.55,
        "raw_cols": "||1.85|3.15|4.55|12-25 23:54|早"
      }
    }
  },
  "counts": {
    "handicap_events": 10,
    "overunder_events": 4,
    "1x2_events": 10
  },
  "meta": {
    "source": "titan",
    "export_ts": "20251226_105444"
  }
}